JiemiCssWaiBowang/README.md
JiemiCssWaiBowang/__init__.py
JiemiCssWaiBowang/__main__.py
JiemiCssWaiBowang/file.epub
JiemiCssWaiBowang/index.html
JiemiCssWaiBowang/css/__init__.py
JiemiCssWaiBowang/css/annotations.css
JiemiCssWaiBowang/css/main.css
JiemiCssWaiBowang/css/normalize.css
JiemiCssWaiBowang/css/popup.css
JiemiCssWaiBowang/font/__init__.py
JiemiCssWaiBowang/font/fontello.eot
JiemiCssWaiBowang/font/fontello.svg
JiemiCssWaiBowang/font/fontello.ttf
JiemiCssWaiBowang/font/fontello.woff
JiemiCssWaiBowang/img/__init__.py
JiemiCssWaiBowang/img/annotator-glyph-sprite.png
JiemiCssWaiBowang/img/annotator-icon-sprite.png
JiemiCssWaiBowang/img/apple-touch-icon.png
JiemiCssWaiBowang/img/cancelfullscreen.png
JiemiCssWaiBowang/img/close.png
JiemiCssWaiBowang/img/fullscreen.png
JiemiCssWaiBowang/img/loader.gif
JiemiCssWaiBowang/img/menu-icon.png
JiemiCssWaiBowang/img/save.png
JiemiCssWaiBowang/img/saved.png
JiemiCssWaiBowang/img/settings-s.png
JiemiCssWaiBowang/img/settings.png
JiemiCssWaiBowang/img/star.png
JiemiCssWaiBowang/js/__init__.py
JiemiCssWaiBowang/js/epub.js
JiemiCssWaiBowang/js/epub.min.js
JiemiCssWaiBowang/js/epub.min.map
JiemiCssWaiBowang/js/hooks.min.js
JiemiCssWaiBowang/js/hooks.min.map
JiemiCssWaiBowang/js/reader.js
JiemiCssWaiBowang/js/reader.js.map
JiemiCssWaiBowang/js/reader.min.js
JiemiCssWaiBowang/js/reader.min.map
JiemiCssWaiBowang/js/hooks/__init__.py
JiemiCssWaiBowang/js/hooks/extensions/__init__.py
JiemiCssWaiBowang/js/hooks/extensions/highlight.js
JiemiCssWaiBowang/js/libs/__init__.py
JiemiCssWaiBowang/js/libs/jquery.min.js
JiemiCssWaiBowang/js/libs/localforage.min.js
JiemiCssWaiBowang/js/libs/screenfull.js
JiemiCssWaiBowang/js/libs/screenfull.min.js
JiemiCssWaiBowang/js/libs/zip.min.js
JiemiCssWaiBowang/js/plugins/__init__.py
JiemiCssWaiBowang/js/plugins/hypothesis.js
JiemiCssWaiBowang/js/plugins/search.js
jiemi_css_wai_bowang-2024.3.3.0.dist-info/METADATA
jiemi_css_wai_bowang-2024.3.3.0.dist-info/WHEEL
jiemi_css_wai_bowang-2024.3.3.0.dist-info/entry_points.txt
jiemi_css_wai_bowang-2024.3.3.0.dist-info/top_level.txt
jiemi_css_wai_bowang-2024.3.3.0.dist-info/RECORD
